HuTuTu/TuTu.py
HuTuTu/__init__.py
HuTuTu-0.0.1.dist-info/LICENSE
HuTuTu-0.0.1.dist-info/METADATA
HuTuTu-0.0.1.dist-info/WHEEL
HuTuTu-0.0.1.dist-info/top_level.txt
HuTuTu-0.0.1.dist-info/RECORD
