Metadata-Version: 2.1
Name: HuTuTu
Version: 0.0.1
Summary: 基于视觉基座模型的图片识别与理解功能库
Home-page: https://github.com/Matrix-King-Studio/TuTu
Author: alex
Author-email: liu_zhao_feng_alex@163.com
Project-URL: Bug Tracker, https://github.com/Matrix-King-Studio/TuTu/issues
Platform: any
Classifier: Programming Language :: Python :: 3
Classifier: License :: OSI Approved :: MIT License
Classifier: Operating System :: OS Independent
Requires-Python: >=3.9
License-File: LICENSE
Requires-Dist: transformers ==4.42.4
